{"actions":"[{'name': 'Like', 'link': 'https://www.facebook.com/441742544607086/posts/766150818832922'}, {'name': 'Comment', 'link': 'https://www.facebook.com/441742544607086/posts/766150818832922'}, {'name': 'Share', 'link': 'https://www.facebook.com/441742544607086/posts/766150818832922'}]","attachments":{"data":"[{'description': 'Tökéletes Vasárnap Este Fűzy Gáborral a MOM Leroy Bistroban!\\n\\nCsatlakozz hozzánk egy felejthetetlen vasárnap estére, ahol Fűzy Gábor, a zongora mestere, újra varázslatot visz a MOM Leroy Bistro hangulatába! Ismerős arcok, nosztalgikus dallamok és a zenei élmény garantált.\\n\\n🎹 Előadó: Fűzy Gábor\\n🎶 Hangulat: Nosztalgikus dallamok és zenei varázslat\\n📅 Időpont: 2024.05.26, vasárnap 19:00\\n\\n📞 Asztalfoglalás: +36 (1) 487 5418\\n\\n#momleroybistro #füzygábor #zongoraest #budapestetterem #buda #mompark', 'media': {'image': {'height': 684, 'src': 'https://scontent-iad3-2.xx.fbcdn.net/v/t39.30808-6/438170097_828167672679947_1799297088024822263_n.jpg?_nc_cat=106&ccb=1-7&_nc_sid=5f2048&_nc_ohc=kmTGbrVJlcAQ7kNvgHIYcnc&_nc_ht=scontent-iad3-2.xx&edm=AKK4YLsEAAAA&oh=00_AYAHfHNKsy-ovG2w-ye8zWbte4o71FNy41cYucc3h2Fn9A&oe=6656AEA4', 'width': 684}}, 'media_type': 'photo', 'target': {'id': '838785561618158', 'url': 'https://www.facebook.com/photo.php?fbid=838785561618158&set=a.471844334978951&type=3'}, 'unshimmed_url': 'https://www.facebook.com/photo.php?fbid=838785561618158&set=a.471844334978951&type=3'}]"},"created_time":"2024-05-24T18:16:07+0000","description":"Tökéletes Vasárnap Este Fűzy Gáborral a MOM Leroy Bistroban!\n\nCsatlakozz hozzánk egy felejthetetlen vasárnap estére, ahol Fűzy Gábor, a zongora mestere, újra varázslatot visz a MOM Leroy Bistro hangulatába! Ismerős arcok, nosztalgikus dallamok és a zenei élmény garantált.\n\n🎹 Előadó: Fűzy Gábor\n🎶 Hangulat: Nosztalgikus dallamok és zenei varázslat\n📅 Időpont: 2024.05.26, vasárnap 19:00\n\n📞 Asztalfoglalás: +36 (1) 487 5418\n\n#momleroybistro #füzygábor #zongoraest #budapestetterem #buda #mompark","first_action":{"link":"https://www.facebook.com/441742544607086/posts/766150818832922","name":"Like"},"from":{"id":"190825651114970","name":"Fűzy Gábor"},"full_picture":"https://scontent-iad3-2.xx.fbcdn.net/v/t39.30808-6/438170097_828167672679947_1799297088024822263_n.jpg?_nc_cat=106&ccb=1-7&_nc_sid=5f2048&_nc_ohc=kmTGbrVJlcAQ7kNvgHIYcnc&_nc_ht=scontent-iad3-2.xx&edm=AKK4YLsEAAAA&oh=00_AYAHfHNKsy-ovG2w-ye8zWbte4o71FNy41cYucc3h2Fn9A&oe=6656AEA4","full_res_picture":"https://scontent-iad3-2.xx.fbcdn.net/v/t39.30808-6/438170097_828167672679947_1799297088024822263_n.jpg?_nc_cat=106&ccb=1-7&_nc_sid=5f2048&_nc_ohc=kmTGbrVJlcAQ7kNvgHIYcnc&_nc_ht=scontent-iad3-2.xx&edm=AKK4YLsEAAAA&oh=00_AYAHfHNKsy-ovG2w-ye8zWbte4o71FNy41cYucc3h2Fn9A&oe=6656AEA4","id":"190825651114970_766150818832922","link":"https://www.facebook.com/photo.php?fbid=838785561618158&set=a.471844334978951&type=3","message":"Igaz, hogy én most még Balatonfüreden vagyok, de vasárnap este mindenképpen találkozunk a MOM Leroy vacsoraestjén! Találkozunk? 🤔\n🎼🎹🕺🏼💃🏼","picture":"https://scontent-iad3-2.xx.fbcdn.net/v/t39.30808-6/438170097_828167672679947_1799297088024822263_n.jpg?stp=dst-jpg_p130x130&_nc_cat=106&ccb=1-7&_nc_sid=5f2048&_nc_ohc=kmTGbrVJlcAQ7kNvgHIYcnc&_nc_ht=scontent-iad3-2.xx&edm=AKK4YLsEAAAA&oh=00_AYB9x1UpTkHzrSQ6gY_eVakpXVxdjV3cqpVhyIGf4IJnwA&oe=6656AEA4","status_type":"mobile_status_update","type":"photo","updated_time":"2024-05-24T18:16:07+0000"}